arcade_accelerate-1.0.2.dist-info/METADATA
arcade_accelerate-1.0.2.dist-info/WHEEL
arcade_accelerate-1.0.2.dist-info/license_files/LICENSE
arcade_accelerate/__init__.py
arcade_accelerate/module_patcher.py
arcade_accelerate/arcade_accelerate.cpython-310-s390x-linux-gnu.so
arcade_accelerate-1.0.2.dist-info/RECORD
