Metadata-Version: 2.1
Name: arcade-accelerate
Version: 1.0.2
Classifier: Programming Language :: Rust
Classifier: Programming Language :: Python :: Implementation :: CPython
Classifier: Programming Language :: Python :: Implementation :: PyPy
Requires-Dist: ruff ; extra == 'dev'
Requires-Dist: black ; extra == 'dev'
Requires-Dist: matplotlib ; extra == 'dev'
Requires-Dist: seaborn ; extra == 'dev'
Provides-Extra: dev
License-File: LICENSE
Summary: A companion library for Arcade providing accelerated Rust functions
Author-email: Darren Eberly <Daren.Eberly@gmail.com>
Maintainer-email: Darren Eberly <Darren.Eberly@gmail.com>
Requires-Python: >=3.7
Project-URL: homepage, https://github.com/pythonarcade/arcade-accelerate
